RealRsa-0.1.0.dist-info/LICENSE
RealRsa-0.1.0.dist-info/top_level.txt
RealRsa-0.1.0.dist-info/RECORD
RealRsa-0.1.0.dist-info/METADATA
RealRsa-0.1.0.dist-info/WHEEL
RealRsa/RealRsa.pyi
RealRsa/__init__.py
RealRsa/RealRsa.cpython-312-x86_64-linux-gnu.so
RealRsa.libs/libssl-284998a2.so.3
RealRsa.libs/libcrypto-d170aa8b.so.3
