Metadata-Version: 2.1
Name: RealRsa
Version: 0.1.0
Summary: python version of rsa
Author: zkh
Author-email: 404937333@qq.com
License: MIT License
Keywords: cryto,openssl
Platform: Windows
Platform: Linux
Classifier: Development Status :: 4 - Beta
Classifier: Intended Audience :: Developers
Classifier: License :: OSI Approved :: MIT License
Classifier: Operating System :: Microsoft :: Windows
Classifier: Natural Language :: Chinese (Simplified)
Classifier: Programming Language :: Python :: 3
Classifier: Topic :: Software Development :: Libraries :: Python Modules
Requires-Python: >=3.8,<4.0
License-File: LICENSE
